{
  "week": "2026年6月第3週",
  "ranking": [
    {
      "rank": 1,
      "item": "キャベツ",
      "score": 90,
      "retail_price": null,
      "reason": "入荷量616t",
      "comment": "入荷量は前週比11%減で価格はやや強保合ですが、今が甘みののる旬で、生食でも加熱でも美味しく使い回しの効くおすすめ品です。"
    },
    {
      "rank": 2,
      "item": "だいこん",
      "score": 83,
      "retail_price": null,
      "reason": "入荷量290t",
      "comment": "入荷量は前週比8%減で青森県産が強保合ですが、みずみずしさが際立つ季節で、煮物・サラダ・大根おろしと幅広く楽しめます。"
    },
    {
      "rank": 3,
      "item": "ほうれんそう",
      "score": 82,
      "retail_price": null,
      "reason": "入荷量65t",
      "comment": "寒さで甘みが増す旬の時期で、栄養価も高くおひたしや炒め物、スープに重宝する一品です。"
    },
    {
      "rank": 4,
      "item": "なす",
      "score": 82,
      "retail_price": null,
      "reason": "入荷量187t",
      "comment": ""
    },
    {
      "rank": 5,
      "item": "ピーマン",
      "score": 81,
      "retail_price": null,
      "reason": "入荷量108t",
      "comment": ""
    }
  ],
  "market_comment": "今週は全体の入荷量が前週比11%減少し、葉物野菜を中心にやや強含みの市況です。キャベツやだいこん、ほうれんそうは旬を迎えており、価格と品質のバランスが良いタイミングです。",
  "recipes": [
    {
      "title": "キャベツとツナの無限サラダ",
      "item": "キャベツ",
      "time_min": 10,
      "servings": "2人分",
      "ingredients": [
        "キャベツ 1/4個",
        "ツナ缶 1缶",
        "ごま油 大さじ1",
        "鶏ガラスープの素 小さじ1",
        "白ごま 適量"
      ],
      "steps": [
        "キャベツを千切りにして耐熱ボウルに入れ、ラップして電子レンジで2分加熱する。",
        "水気を切り、ツナ・ごま油・鶏ガラスープの素を加えて和える。",
        "白ごまをふって完成。"
      ]
    },
    {
      "title": "だいこんと鶏肉のさっぱり煮",
      "item": "だいこん",
      "time_min": 30,
      "servings": "2人分",
      "ingredients": [
        "だいこん 1/2本",
        "鶏もも肉 200g",
        "醤油 大さじ2",
        "みりん 大さじ2",
        "酢 大さじ1",
        "水 300ml"
      ],
      "steps": [
        "だいこんは輪切りにして面取りし、鶏もも肉は一口大に切る。",
        "鍋に全ての材料を入れて中火にかけ、煮立ったら弱火で20分煮る。",
        "だいこんが柔らかくなり、味が染みたら完成。"
      ]
    },
    {
      "title": "ほうれんそうのごま和え",
      "item": "ほうれんそう",
      "time_min": 10,
      "servings": "2人分",
      "ingredients": [
        "ほうれんそう 1束",
        "すりごま 大さじ2",
        "醤油 小さじ2",
        "砂糖 小さじ1"
      ],
      "steps": [
        "ほうれんそうを塩ゆでし、冷水にとって水気を絞り3cm幅に切る。",
        "ボウルにすりごま・醤油・砂糖を混ぜ、ほうれんそうを和える。",
        "器に盛って完成。"
      ]
    }
  ]
}