{
  "description": "消費者向け『おすすめ野菜スコア』は、供給の豊富さ・トレンド性・旬の度合い・価格の手頃さを統計的に正規化して重み付け合成した0～100点の指標です。各因子は全品目の最大値または基準値でMin-Max正規化し、価格因子のみ逆数変換して『安いほど高得点』となるよう設計しています。重みは消費者行動調査で重視されやすい『価格』と『入手しやすさ』を優先配分しました。",
  "factors": [
    {
      "name": "豊富さスコア (Abundance)",
      "source": "入荷量（t）",
      "weight": 0.3,
      "formula": "A = (入荷量 / max_入荷量) * 100",
      "notes": "全品目中で最も入荷量が多い野菜を100点として正規化。供給が潤沢なほど店頭で確実に入手でき、鮮度回転も良い。"
    },
    {
      "name": "トレンドスコア (Trend)",
      "source": "前週比（%）",
      "weight": 0.15,
      "formula": "T = min(max((前週比 - 50) / 100 * 100, 0), 100)",
      "notes": "前週比50%を下限、150%を上限としてクリッピング。供給増加は市場での注目度・生産者の出荷意欲の高さを示す。"
    },
    {
      "name": "旬スコア (Seasonality)",
      "source": "前年比（%）",
      "weight": 0.2,
      "formula": "S = 100 - min(|前年比 - 100| / 50 * 100, 100)",
      "notes": "前年同時期と同水準（100%）に近いほど『例年通りの旬』として高得点。極端に多い/少ない場合は異常値として減点。"
    },
    {
      "name": "手頃さスコア (Affordability)",
      "source": "価格（円）",
      "weight": 0.35,
      "formula": "P = (1 - (価格 - min_価格) / (max_価格 - min_価格)) * 100",
      "notes": "全品目中で最安値を100点、最高値を0点として逆Min-Max正規化。家計インパクトが最大なため最高重みを配分。"
    }
  ],
  "final_score_formula": "Score = 0.30 * A + 0.15 * T + 0.20 * S + 0.35 * P  （0～100点にクリップ）",
  "example": "例：キャベツの場合、入荷量500t（max=800t）、前週比120%、前年比105%、価格150円（min=100円, max=400円）。\n・A = (500/800)*100 = 62.5\n・T = ((120-50)/100)*100 = 70.0\n・S = 100 - (|105-100|/50)*100 = 90.0\n・P = (1 - (150-100)/(400-100))*100 = 83.3\n・Score = 0.30*62.5 + 0.15*70.0 + 0.20*90.0 + 0.35*83.3 = 18.75 + 10.5 + 18.0 + 29.16 ≈ 76.4点 → 『おすすめ度：高』"
}