{
  "week": "2026年5月第4週",
  "ranking_comments": {
    "ピーマン": "今が旬で果肉が肉厚、ビタミンCたっぷり。価格も手頃で、炒め物や肉詰めにぴったりです。",
    "にら": "香り高くスタミナ食材の代表格、価格も安定しており、餃子や卵とじ、レバニラ炒めで手軽に楽しめます。",
    "こまつな": "クセが少なくカルシウム豊富、価格も安定。下茹で不要で炒め物やおひたし、味噌汁にすぐ使えて便利です。"
  },
  "market_comment": "今週は全体の入荷量が前週比1%減と落ち着いた動きですが、キャベツやレタスは入荷増で価格は弱保合。緑黄色野菜のピーマン・にら・こまつなが旬を迎え、お買い得かつ栄養満点でおすすめです。",
  "recipes": [
    {
      "title": "ピーマンの無限おかか和え",
      "item": "ピーマン",
      "time_min": 10,
      "servings": "2人分",
      "ingredients": [
        "ピーマン 4個",
        "ごま油 大さじ1",
        "鰹節 1パック",
        "醤油 小さじ2",
        "白ごま 適量"
      ],
      "steps": [
        "ピーマンを細切りにする",
        "耐熱ボウルに入れごま油を絡めてレンジで2分加熱する",
        "鰹節・醤油・白ごまを加えて和える"
      ]
    },
    {
      "title": "にらと卵のふんわり炒め",
      "item": "にら",
      "time_min": 8,
      "servings": "2人分",
      "ingredients": [
        "にら 1束",
        "卵 2個",
        "鶏がらスープの素 小さじ1",
        "塩こしょう 少々",
        "ごま油 大さじ1"
      ],
      "steps": [
        "にらは4cm幅に切る",
        "溶き卵を半熟に炒めて一度取り出す",
        "同じフライパンでにらを炒め鶏がらスープと塩こしょうで味付け、卵を戻して軽く炒め合わせる"
      ]
    },
    {
      "title": "こまつなとツナのさっと煮",
      "item": "こまつな",
      "time_min": 10,
      "servings": "2人分",
      "ingredients": [
        "こまつな 1束",
        "ツナ缶 1缶",
        "だし汁 100ml",
        "醤油 大さじ1",
        "みりん 大さじ1"
      ],
      "steps": [
        "こまつなを4cm幅に切る",
        "鍋にだし汁・醤油・みりんとツナを入れ煮立てる",
        "こまつなを加えしんなりするまで2分ほど煮る"
      ]
    }
  ]
}